MANIFEST.in
README.md
setup.py
Flask_Docs_Cat.egg-info/PKG-INFO
Flask_Docs_Cat.egg-info/SOURCES.txt
Flask_Docs_Cat.egg-info/dependency_links.txt
Flask_Docs_Cat.egg-info/not-zip-safe
Flask_Docs_Cat.egg-info/requires.txt
Flask_Docs_Cat.egg-info/top_level.txt
flask_docs/__init__.py
flask_docs/assets/sample_app_add.png
flask_docs/assets/sample_app_del.png
flask_docs/assets/sample_app_get.png
flask_docs/assets/sample_app_restful_get.png
flask_docs/assets/sample_app_restful_post.png
flask_docs/static/FileSaver.min.js
flask_docs/static/index.css
flask_docs/static/index.js
flask_docs/static/jquery.js
flask_docs/static/jquery.jsonview.css
flask_docs/static/jquery.jsonview.js
flask_docs/static/marked.min.js
flask_docs/static/vue.min.js
flask_docs/static/fonts/element-icons.ttf
flask_docs/static/fonts/element-icons.woff
flask_docs/templates/apidoc/api_doc.html
flask_docs/templates/apidoc/base.html