Metadata-Version: 2.1
Name: Flask-Docs-Cat
Version: 0.1.4
Summary: Adds Docs support to Flask.
Home-page: https://github.com/cooler1217/flask-docs
Author: cooler1217
Author-email: 418435432@qq.com
License: MIT
Keywords: flask,api,apidoc,doc,docs,documentation,md,markdown,RESTful,auto
Platform: any
Classifier: Environment :: Web Environment
Classifier: Intended Audience :: Developers
Classifier: License :: OSI Approved :: MIT License
Classifier: Operating System :: OS Independent
Classifier: Programming Language :: Python
Classifier: Programming Language :: Python :: 2
Classifier: Programming Language :: Python :: 3
Classifier: Topic :: Internet :: WWW/HTTP :: Dynamic Content
Classifier: Topic :: Software Development :: Libraries :: Python Modules
